{"\u0432\u044b\u043a\u0443\u043f": ["V", "Y", "K", "U", "P"], "\u0431\u0443\u0431\u0435\u043d": ["B", "U", "B", "I", "N"], "\u0442\u0435\u0437\u0438\u0441": ["T", "E", "Z", "I", "S"], "\u043f\u043e\u043b\u044e\u0441": ["P", "O", "L", "U", "S"], "\u0432\u044b\u0437\u043e\u0432": ["V", "Y", "Z", "A", "F"], "\u0444\u043e\u0440\u0443\u043c": ["F", "O", "R", "U", "M"], "\u0433\u0435\u043b\u0438\u0439": ["G", "E", "L", "I", "J0"], "\u043d\u0430\u0432\u044b\u043a": ["N", "A", "V", "Y", "K"], "\u0433\u043e\u0440\u043e\u0434": ["G", "O", "R", "A", "T"], "\u0434\u043e\u043c\u0438\u043a": ["D", "O", "M", "I", "K"], "\u0432\u044b\u0434\u0430\u043b": ["V", "Y", "D", "A", "L"], "\u043b\u043e\u043f\u0430\u043b": ["L", "O", "P", "A", "L"], "\u043c\u0435\u0440\u0438\u0442": ["M", "E", "R", "I", "T"], "\u0441\u0443\u0437\u0438\u0442": ["S", "U", "Z", "I", "T"], "\u043a\u0438\u043d\u0443\u043b": ["K", "I", "N", "U", "L"], "\u0441\u043e\u0442\u044b\u0439": ["S", "O", "T", "Y", "J0"], "\u043c\u0430\u043c\u0438\u043d": ["M", "A", "M", "I", "N"], "\u0434\u0435\u0434\u043e\u0432": ["D", "E", "D", "A", "F"], "\u0431\u0443\u0440\u044b\u0439": ["B", "U", "R", "Y", "J0"], "\u043f\u0435\u0433\u0438\u0439": ["P", "E", "G", "I", "J0"]}